{"trial_id": "02", "hyperparameters": {"space": [{"class_name": "Int", "config": {"name": "units", "default": null, "conditions": [], "min_value": 8, "max_value": 64, "step": 8, "sampling": "linear"}}, {"class_name": "Choice", "config": {"name": "activation", "default": "relu", "conditions": [], "values": ["relu", "tanh"], "ordered": false}}, {"class_name": "Float", "config": {"name": "lr", "default": 0.0001, "conditions": [], "min_value": 0.0001, "max_value": 0.3, "step": null, "sampling": "log"}}], "values": {"units": 16, "activation": "tanh", "lr": 0.16438743694138194}}, "metrics": {"metrics": {"loss": {"direction": "min", "observations": [{"value": [773.2340698242188], "step": 1}]}, "mse": {"direction": "min", "observations": [{"value": [1461018.975], "step": 1}]}, "mae": {"direction": "min", "observations": [{"value": [773.2340698242188], "step": 1}]}, "val_loss": {"direction": "min", "observations": [{"value": [661.5733764648437], "step": 1}]}, "val_mse": {"direction": "min", "observations": [{"value": [2752615.3], "step": 1}]}, "val_mae": {"direction": "min", "observations": [{"value": [661.5733764648437], "step": 1}]}}}, "score": 661.5733764648437, "best_step": 1, "status": "COMPLETED", "message": null}